Metadata-Version: 1.0
Name: grope
Version: 2.0.1
Summary: Generalized rope data structure
Home-page: https://github.com/avakar/grope
Author: Martin Vejnár
Author-email: vejnar.martin@gmail.com
License: MIT
Platform: UNKNOWN
